jwt/__init__.py
jwt/exceptions.py
jwt/jwa.py
jwt/jwk.py
jwt/jwkset.py
jwt/jws.py
jwt/jwt.py
jwt/py.typed
jwt/utils.py
jwt-1.3.0.dist-info/LICENSE
jwt-1.3.0.dist-info/METADATA
jwt-1.3.0.dist-info/WHEEL
jwt-1.3.0.dist-info/top_level.txt
jwt-1.3.0.dist-info/RECORD
