Metadata-Version: 1.2
Name: jwt
Version: 1.3.0
Summary: JSON Web Token library for Python 3.
Home-page: https://github.com/GehirnInc/python-jwt
Author: Kohei YOSHIDA
Author-email: kohei.yoshida@gehirn.co.jp
License: UNKNOWN
Platform: UNKNOWN
Classifier: Development Status :: 5 - Production/Stable
Classifier: Intended Audience :: Developers
Classifier: License :: OSI Approved :: Apache Software License
Classifier: Operating System :: OS Independent
Classifier: Programming Language :: Python
Classifier: Programming Language :: Python :: 3.6
Classifier: Programming Language :: Python :: 3.7
Classifier: Programming Language :: Python :: 3.8
Classifier: Topic :: Internet :: WWW/HTTP
Classifier: Topic :: Security
Classifier: Topic :: Software Development :: Libraries :: Python Modules
Requires-Python: >= 3.6
